topsis/__init__.py
topsis/__main__.py
TOPSIS_Sanyam_101803298-1.0.0.dist-info/LICENSE.txt
TOPSIS_Sanyam_101803298-1.0.0.dist-info/METADATA
TOPSIS_Sanyam_101803298-1.0.0.dist-info/WHEEL
TOPSIS_Sanyam_101803298-1.0.0.dist-info/entry_points.txt
TOPSIS_Sanyam_101803298-1.0.0.dist-info/top_level.txt
TOPSIS_Sanyam_101803298-1.0.0.dist-info/RECORD
